{
  "full amount; receiver: ->enableCollateral": "113749",
  "full amount; receiver: ->enableCollateral; transferFrom": "123060",
  "full amount; sender: ->disableCollateral;": "96766",
  "full amount; sender: ->disableCollateral; receiver: ->enableCollateral": "113866",
  "full amount; sender: ->disableCollateral; receiver: ->enableCollateral; transferFrom": "123177",
  "full amount; sender: ->disableCollateral; receiver: dirty, ->enableCollateral": "113866",
  "full amount; sender: ->disableCollateral; receiver: dirty, ->enableCollateral; transferFrom": "123177",
  "full amount; sender: ->disableCollateral; transferFrom": "106077",
  "full amount; sender: collateralDisabled": "96649",
  "full amount; sender: collateralDisabled; transferFrom": "105960",
  "partial amount; sender: collateralDisabled;": "96625",
  "partial amount; sender: collateralDisabled; receiver: ->enableCollateral": "113725",
  "partial amount; sender: collateralDisabled; receiver: ->enableCollateral; transferFrom": "118236",
  "partial amount; sender: collateralDisabled; transferFrom": "101136",
  "partial amount; sender: collateralEnabled;": "96833",
  "partial amount; sender: collateralEnabled; receiver: ->enableCollateral": "113933",
  "partial amount; sender: collateralEnabled; receiver: ->enableCollateral; transferFrom": "118444",
  "partial amount; sender: collateralEnabled; transferFrom": "101344"
}